[
  {
    "name": "Rowlet & Alolan Exeggutor-GX",
    "number": "1",
    "rarity": "Rare Holo GX",
    "set_name": "Unified Minds",
    "set_series": "Sun & Moon"
  },
  {
    "name": "Yanma",
    "number": "2",
    "rarity": "Common",
    "set_name": "Unified Minds",
    "set_series": "Sun & Moon"
  },
  {
    "name": "Yanmega",
    "number": "3",
    "rarity": "Uncommon",
    "set_name": "Unified Minds",
    "set_series": "Sun & Moon"
  },
  {
    "name": "Celebi",
    "number": "4",
    "rarity": "Rare Holo",
    "set_name": "Unified Minds",
    "set_series": "Sun & Moon"
  },
  {
    "name": "Shroomish",
    "number": "5",
    "rarity": "Common",
    "set_name": "Unified Minds",
    "set_series": "Sun & Moon"
  },
  {
    "name": "Sewaddle",
    "number": "6",
    "rarity": "Common",
    "set_name": "Unified Minds",
    "set_series": "Sun & Moon"
  },
  {
    "name": "Sewaddle",
    "number": "7",
    "rarity": "Common",
    "set_name": "Unified Minds",
    "set_series": "Sun & Moon"
  },
  {
    "name": "Swadloon",
    "number": "8",
    "rarity": "Uncommon",
    "set_name": "Unified Minds",
    "set_series": "Sun & Moon"
  },
  {
    "name": "Leavanny",
    "number": "9",
    "rarity": "Rare",
    "set_name": "Unified Minds",
    "set_series": "Sun & Moon"
  },
  {
    "name": "Dwebble",
    "number": "10",
    "rarity": "Common",
    "set_name": "Unified Minds",
    "set_series": "Sun & Moon"
  },
  {
    "name": "Crustle",
    "number": "11",
    "rarity": "Rare",
    "set_name": "Unified Minds",
    "set_series": "Sun & Moon"
  },
  {
    "name": "Karrablast",
    "number": "12",
    "rarity": "Common",
    "set_name": "Unified Minds",
    "set_series": "Sun & Moon"
  },
  {
    "name": "Foongus",
    "number": "13",
    "rarity": "Common",
    "set_name": "Unified Minds",
    "set_series": "Sun & Moon"
  },
  {
    "name": "Amoonguss",
    "number": "14",
    "rarity": "Rare",
    "set_name": "Unified Minds",
    "set_series": "Sun & Moon"
  },
  {
    "name": "Fomantis",
    "number": "15",
    "rarity": "Common",
    "set_name": "Unified Minds",
    "set_series": "Sun & Moon"
  },
  {
    "name": "Lurantis",
    "number": "16",
    "rarity": "Uncommon",
    "set_name": "Unified Minds",
    "set_series": "Sun & Moon"
  },
  {
    "name": "Bounsweet",
    "number": "17",
    "rarity": "Common",
    "set_name": "Unified Minds",
    "set_series": "Sun & Moon"
  },
  {
    "name": "Steenee",
    "number": "18",
    "rarity": "Uncommon",
    "set_name": "Unified Minds",
    "set_series": "Sun & Moon"
  },
  {
    "name": "Tsareena",
    "number": "19",
    "rarity": "Rare Holo",
    "set_name": "Unified Minds",
    "set_series": "Sun & Moon"
  },
  {
    "name": "Dhelmise",
    "number": "20",
    "rarity": "Uncommon",
    "set_name": "Unified Minds",
    "set_series": "Sun & Moon"
  },
  {
    "name": "Magmar",
    "number": "21",
    "rarity": "Common",
    "set_name": "Unified Minds",
    "set_series": "Sun & Moon"
  },
  {
    "name": "Magmortar",
    "number": "22",
    "rarity": "Rare",
    "set_name": "Unified Minds",
    "set_series": "Sun & Moon"
  },
  {
    "name": "Numel",
    "number": "23",
    "rarity": "Common",
    "set_name": "Unified Minds",
    "set_series": "Sun & Moon"
  },
  {
    "name": "Camerupt",
    "number": "24",
    "rarity": "Rare",
    "set_name": "Unified Minds",
    "set_series": "Sun & Moon"
  },
  {
    "name": "Heatran-GX",
    "number": "25",
    "rarity": "Rare Holo GX",
    "set_name": "Unified Minds",
    "set_series": "Sun & Moon"
  },
  {
    "name": "Victini",
    "number": "26",
    "rarity": "Rare Holo",
    "set_name": "Unified Minds",
    "set_series": "Sun & Moon"
  },
  {
    "name": "Litwick",
    "number": "27",
    "rarity": "Common",
    "set_name": "Unified Minds",
    "set_series": "Sun & Moon"
  },
  {
    "name": "Litwick",
    "number": "28",
    "rarity": "Common",
    "set_name": "Unified Minds",
    "set_series": "Sun & Moon"
  },
  {
    "name": "Lampent",
    "number": "29",
    "rarity": "Uncommon",
    "set_name": "Unified Minds",
    "set_series": "Sun & Moon"
  },
  {
    "name": "Chandelure",
    "number": "30",
    "rarity": "Rare Holo",
    "set_name": "Unified Minds",
    "set_series": "Sun & Moon"
  },
  {
    "name": "Fletchinder",
    "number": "31",
    "rarity": "Common",
    "set_name": "Unified Minds",
    "set_series": "Sun & Moon"
  },
  {
    "name": "Talonflame",
    "number": "32",
    "rarity": "Rare",
    "set_name": "Unified Minds",
    "set_series": "Sun & Moon"
  },
  {
    "name": "Salandit",
    "number": "33",
    "rarity": "Common",
    "set_name": "Unified Minds",
    "set_series": "Sun & Moon"
  },
  {
    "name": "Salazzle",
    "number": "34",
    "rarity": "Rare",
    "set_name": "Unified Minds",
    "set_series": "Sun & Moon"
  },
  {
    "name": "Slowpoke & Psyduck-GX",
    "number": "35",
    "rarity": "Rare Holo GX",
    "set_name": "Unified Minds",
    "set_series": "Sun & Moon"
  },
  {
    "name": "Lapras",
    "number": "36",
    "rarity": "Uncommon",
    "set_name": "Unified Minds",
    "set_series": "Sun & Moon"
  },
  {
    "name": "Snorunt",
    "number": "37",
    "rarity": "Common",
    "set_name": "Unified Minds",
    "set_series": "Sun & Moon"
  },
  {
    "name": "Froslass",
    "number": "38",
    "rarity": "Rare Holo",
    "set_name": "Unified Minds",
    "set_series": "Sun & Moon"
  },
  {
    "name": "Finneon",
    "number": "39",
    "rarity": "Common",
    "set_name": "Unified Minds",
    "set_series": "Sun & Moon"
  },
  {
    "name": "Lumineon",
    "number": "40",
    "rarity": "Uncommon",
    "set_name": "Unified Minds",
    "set_series": "Sun & Moon"
  },
  {
    "name": "Snover",
    "number": "41",
    "rarity": "Common",
    "set_name": "Unified Minds",
    "set_series": "Sun & Moon"
  },
  {
    "name": "Abomasnow",
    "number": "42",
    "rarity": "Rare",
    "set_name": "Unified Minds",
    "set_series": "Sun & Moon"
  },
  {
    "name": "Basculin",
    "number": "43",
    "rarity": "Uncommon",
    "set_name": "Unified Minds",
    "set_series": "Sun & Moon"
  },
  {
    "name": "Tirtouga",
    "number": "44",
    "rarity": "Uncommon",
    "set_name": "Unified Minds",
    "set_series": "Sun & Moon"
  },
  {
    "name": "Carracosta",
    "number": "45",
    "rarity": "Uncommon",
    "set_name": "Unified Minds",
    "set_series": "Sun & Moon"
  },
  {
    "name": "Cryogonal",
    "number": "46",
    "rarity": "Common",
    "set_name": "Unified Minds",
    "set_series": "Sun & Moon"
  },
  {
    "name": "Keldeo-GX",
    "number": "47",
    "rarity": "Rare Holo GX",
    "set_name": "Unified Minds",
    "set_series": "Sun & Moon"
  },
  {
    "name": "Dewpider",
    "number": "48",
    "rarity": "Common",
    "set_name": "Unified Minds",
    "set_series": "Sun & Moon"
  },
  {
    "name": "Araquanid",
    "number": "49",
    "rarity": "Rare",
    "set_name": "Unified Minds",
    "set_series": "Sun & Moon"
  },
  {
    "name": "Wimpod",
    "number": "50",
    "rarity": "Common",
    "set_name": "Unified Minds",
    "set_series": "Sun & Moon"
  },
  {
    "name": "Golisopod",
    "number": "51",
    "rarity": "Rare Holo",
    "set_name": "Unified Minds",
    "set_series": "Sun & Moon"
  },
  {
    "name": "Pyukumuku",
    "number": "52",
    "rarity": "Uncommon",
    "set_name": "Unified Minds",
    "set_series": "Sun & Moon"
  },
  {
    "name": "Tapu Fini",
    "number": "53",
    "rarity": "Rare",
    "set_name": "Unified Minds",
    "set_series": "Sun & Moon"
  },
  {
    "name": "Raichu & Alolan Raichu-GX",
    "number": "54",
    "rarity": "Rare Holo GX",
    "set_name": "Unified Minds",
    "set_series": "Sun & Moon"
  },
  {
    "name": "Pikachu",
    "number": "55",
    "rarity": "Common",
    "set_name": "Unified Minds",
    "set_series": "Sun & Moon"
  },
  {
    "name": "Pikachu",
    "number": "56",
    "rarity": "Common",
    "set_name": "Unified Minds",
    "set_series": "Sun & Moon"
  },
  {
    "name": "Alolan Raichu",
    "number": "57",
    "rarity": "Rare Holo",
    "set_name": "Unified Minds",
    "set_series": "Sun & Moon"
  },
  {
    "name": "Magnemite",
    "number": "58",
    "rarity": "Common",
    "set_name": "Unified Minds",
    "set_series": "Sun & Moon"
  },
  {
    "name": "Magneton",
    "number": "59",
    "rarity": "Uncommon",
    "set_name": "Unified Minds",
    "set_series": "Sun & Moon"
  },
  {
    "name": "Magnezone",
    "number": "60",
    "rarity": "Rare Holo",
    "set_name": "Unified Minds",
    "set_series": "Sun & Moon"
  },
  {
    "name": "Joltik",
    "number": "61",
    "rarity": "Common",
    "set_name": "Unified Minds",
    "set_series": "Sun & Moon"
  },
  {
    "name": "Galvantula",
    "number": "62",
    "rarity": "Rare",
    "set_name": "Unified Minds",
    "set_series": "Sun & Moon"
  },
  {
    "name": "Tynamo",
    "number": "63",
    "rarity": "Common",
    "set_name": "Unified Minds",
    "set_series": "Sun & Moon"
  },
  {
    "name": "Tynamo",
    "number": "64",
    "rarity": "Common",
    "set_name": "Unified Minds",
    "set_series": "Sun & Moon"
  },
  {
    "name": "Eelektrik",
    "number": "65",
    "rarity": "Uncommon",
    "set_name": "Unified Minds",
    "set_series": "Sun & Moon"
  },
  {
    "name": "Eelektross",
    "number": "66",
    "rarity": "Rare Holo",
    "set_name": "Unified Minds",
    "set_series": "Sun & Moon"
  },
  {
    "name": "Stunfisk",
    "number": "67",
    "rarity": "Common",
    "set_name": "Unified Minds",
    "set_series": "Sun & Moon"
  },
  {
    "name": "Thundurus",
    "number": "68",
    "rarity": "Uncommon",
    "set_name": "Unified Minds",
    "set_series": "Sun & Moon"
  },
  {
    "name": "Tapu Koko",
    "number": "69",
    "rarity": "Rare Holo",
    "set_name": "Unified Minds",
    "set_series": "Sun & Moon"
  },
  {
    "name": "Xurkitree",
    "number": "70",
    "rarity": "Rare",
    "set_name": "Unified Minds",
    "set_series": "Sun & Moon"
  },
  {
    "name": "Mewtwo & Mew-GX",
    "number": "71",
    "rarity": "Rare Holo GX",
    "set_name": "Unified Minds",
    "set_series": "Sun & Moon"
  },
  {
    "name": "Espeon & Deoxys-GX",
    "number": "72",
    "rarity": "Rare Holo GX",
    "set_name": "Unified Minds",
    "set_series": "Sun & Moon"
  },
  {
    "name": "Exeggcute",
    "number": "73",
    "rarity": "Common",
    "set_name": "Unified Minds",
    "set_series": "Sun & Moon"
  },
  {
    "name": "Exeggutor",
    "number": "74",
    "rarity": "Rare",
    "set_name": "Unified Minds",
    "set_series": "Sun & Moon"
  },
  {
    "name": "Alolan Marowak",
    "number": "75",
    "rarity": "Rare",
    "set_name": "Unified Minds",
    "set_series": "Sun & Moon"
  },
  {
    "name": "Jynx",
    "number": "76",
    "rarity": "Uncommon",
    "set_name": "Unified Minds",
    "set_series": "Sun & Moon"
  },
  {
    "name": "Wynaut",
    "number": "77",
    "rarity": "Uncommon",
    "set_name": "Unified Minds",
    "set_series": "Sun & Moon"
  },
  {
    "name": "Latios-GX",
    "number": "78",
    "rarity": "Rare Holo GX",
    "set_name": "Unified Minds",
    "set_series": "Sun & Moon"
  },
  {
    "name": "Jirachi-GX",
    "number": "79",
    "rarity": "Rare Holo GX",
    "set_name": "Unified Minds",
    "set_series": "Sun & Moon"
  },
  {
    "name": "Drifloon",
    "number": "80",
    "rarity": "Common",
    "set_name": "Unified Minds",
    "set_series": "Sun & Moon"
  },
  {
    "name": "Drifblim",
    "number": "81",
    "rarity": "Rare",
    "set_name": "Unified Minds",
    "set_series": "Sun & Moon"
  },
  {
    "name": "Skorupi",
    "number": "82",
    "rarity": "Common",
    "set_name": "Unified Minds",
    "set_series": "Sun & Moon"
  },
  {
    "name": "Uxie",
    "number": "83",
    "rarity": "Rare Holo",
    "set_name": "Unified Minds",
    "set_series": "Sun & Moon"
  },
  {
    "name": "Mesprit",
    "number": "84",
    "rarity": "Uncommon",
    "set_name": "Unified Minds",
    "set_series": "Sun & Moon"
  },
  {
    "name": "Azelf",
    "number": "85",
    "rarity": "Uncommon",
    "set_name": "Unified Minds",
    "set_series": "Sun & Moon"
  },
  {
    "name": "Giratina",
    "number": "86",
    "rarity": "Rare Holo",
    "set_name": "Unified Minds",
    "set_series": "Sun & Moon"
  },
  {
    "name": "Cresselia",
    "number": "87",
    "rarity": "Uncommon",
    "set_name": "Unified Minds",
    "set_series": "Sun & Moon"
  },
  {
    "name": "Munna",
    "number": "88",
    "rarity": "Common",
    "set_name": "Unified Minds",
    "set_series": "Sun & Moon"
  },
  {
    "name": "Musharna",
    "number": "89",
    "rarity": "Uncommon",
    "set_name": "Unified Minds",
    "set_series": "Sun & Moon"
  },
  {
    "name": "Elgyem",
    "number": "90",
    "rarity": "Uncommon",
    "set_name": "Unified Minds",
    "set_series": "Sun & Moon"
  },
  {
    "name": "Beheeyem",
    "number": "91",
    "rarity": "Rare",
    "set_name": "Unified Minds",
    "set_series": "Sun & Moon"
  },
  {
    "name": "Honedge",
    "number": "92",
    "rarity": "Common",
    "set_name": "Unified Minds",
    "set_series": "Sun & Moon"
  },
  {
    "name": "Honedge",
    "number": "93",
    "rarity": "Common",
    "set_name": "Unified Minds",
    "set_series": "Sun & Moon"
  },
  {
    "name": "Doublade",
    "number": "94",
    "rarity": "Uncommon",
    "set_name": "Unified Minds",
    "set_series": "Sun & Moon"
  },
  {
    "name": "Aegislash",
    "number": "95",
    "rarity": "Rare Holo",
    "set_name": "Unified Minds",
    "set_series": "Sun & Moon"
  },
  {
    "name": "Mareanie",
    "number": "96",
    "rarity": "Common",
    "set_name": "Unified Minds",
    "set_series": "Sun & Moon"
  },
  {
    "name": "Toxapex",
    "number": "97",
    "rarity": "Rare",
    "set_name": "Unified Minds",
    "set_series": "Sun & Moon"
  },
  {
    "name": "Salandit",
    "number": "98",
    "rarity": "Common",
    "set_name": "Unified Minds",
    "set_series": "Sun & Moon"
  },
  {
    "name": "Salazzle",
    "number": "99",
    "rarity": "Rare",
    "set_name": "Unified Minds",
    "set_series": "Sun & Moon"
  },
  {
    "name": "Cosmog",
    "number": "100",
    "rarity": "Common",
    "set_name": "Unified Minds",
    "set_series": "Sun & Moon"
  },
  {
    "name": "Necrozma",
    "number": "101",
    "rarity": "Rare",
    "set_name": "Unified Minds",
    "set_series": "Sun & Moon"
  },
  {
    "name": "Poipole",
    "number": "102",
    "rarity": "Common",
    "set_name": "Unified Minds",
    "set_series": "Sun & Moon"
  },
  {
    "name": "Onix",
    "number": "103",
    "rarity": "Common",
    "set_name": "Unified Minds",
    "set_series": "Sun & Moon"
  },
  {
    "name": "Steelix",
    "number": "104",
    "rarity": "Rare",
    "set_name": "Unified Minds",
    "set_series": "Sun & Moon"
  },
  {
    "name": "Cubone",
    "number": "105",
    "rarity": "Common",
    "set_name": "Unified Minds",
    "set_series": "Sun & Moon"
  },
  {
    "name": "Aerodactyl-GX",
    "number": "106",
    "rarity": "Rare Holo GX",
    "set_name": "Unified Minds",
    "set_series": "Sun & Moon"
  },
  {
    "name": "Heracross",
    "number": "107",
    "rarity": "Uncommon",
    "set_name": "Unified Minds",
    "set_series": "Sun & Moon"
  },
  {
    "name": "Breloom",
    "number": "108",
    "rarity": "Uncommon",
    "set_name": "Unified Minds",
    "set_series": "Sun & Moon"
  },
  {
    "name": "Meditite",
    "number": "109",
    "rarity": "Common",
    "set_name": "Unified Minds",
    "set_series": "Sun & Moon"
  },
  {
    "name": "Medicham",
    "number": "110",
    "rarity": "Rare",
    "set_name": "Unified Minds",
    "set_series": "Sun & Moon"
  },
  {
    "name": "Relicanth",
    "number": "111",
    "rarity": "Uncommon",
    "set_name": "Unified Minds",
    "set_series": "Sun & Moon"
  },
  {
    "name": "Gible",
    "number": "112",
    "rarity": "Common",
    "set_name": "Unified Minds",
    "set_series": "Sun & Moon"
  },
  {
    "name": "Gabite",
    "number": "113",
    "rarity": "Uncommon",
    "set_name": "Unified Minds",
    "set_series": "Sun & Moon"
  },
  {
    "name": "Garchomp",
    "number": "114",
    "rarity": "Rare Holo",
    "set_name": "Unified Minds",
    "set_series": "Sun & Moon"
  },
  {
    "name": "Riolu",
    "number": "115",
    "rarity": "Common",
    "set_name": "Unified Minds",
    "set_series": "Sun & Moon"
  },
  {
    "name": "Riolu",
    "number": "116",
    "rarity": "Common",
    "set_name": "Unified Minds",
    "set_series": "Sun & Moon"
  },
  {
    "name": "Lucario",
    "number": "117",
    "rarity": "Rare",
    "set_name": "Unified Minds",
    "set_series": "Sun & Moon"
  },
  {
    "name": "Drilbur",
    "number": "118",
    "rarity": "Common",
    "set_name": "Unified Minds",
    "set_series": "Sun & Moon"
  },
  {
    "name": "Excadrill",
    "number": "119",
    "rarity": "Rare",
    "set_name": "Unified Minds",
    "set_series": "Sun & Moon"
  },
  {
    "name": "Archen",
    "number": "120",
    "rarity": "Uncommon",
    "set_name": "Unified Minds",
    "set_series": "Sun & Moon"
  },
  {
    "name": "Archeops",
    "number": "121",
    "rarity": "Rare",
    "set_name": "Unified Minds",
    "set_series": "Sun & Moon"
  },
  {
    "name": "Terrakion",
    "number": "122",
    "rarity": "Rare Holo",
    "set_name": "Unified Minds",
    "set_series": "Sun & Moon"
  },
  {
    "name": "Meloetta",
    "number": "123",
    "rarity": "Rare",
    "set_name": "Unified Minds",
    "set_series": "Sun & Moon"
  },
  {
    "name": "Zygarde",
    "number": "124",
    "rarity": "Rare",
    "set_name": "Unified Minds",
    "set_series": "Sun & Moon"
  },
  {
    "name": "Umbreon & Darkrai-GX",
    "number": "125",
    "rarity": "Rare Holo GX",
    "set_name": "Unified Minds",
    "set_series": "Sun & Moon"
  },
  {
    "name": "Mega Sableye & Tyranitar-GX",
    "number": "126",
    "rarity": "Rare Holo GX",
    "set_name": "Unified Minds",
    "set_series": "Sun & Moon"
  },
  {
    "name": "Alolan Grimer",
    "number": "127",
    "rarity": "Common",
    "set_name": "Unified Minds",
    "set_series": "Sun & Moon"
  },
  {
    "name": "Murkrow",
    "number": "128",
    "rarity": "Common",
    "set_name": "Unified Minds",
    "set_series": "Sun & Moon"
  },
  {
    "name": "Murkrow",
    "number": "129",
    "rarity": "Common",
    "set_name": "Unified Minds",
    "set_series": "Sun & Moon"
  },
  {
    "name": "Honchkrow",
    "number": "130",
    "rarity": "Rare",
    "set_name": "Unified Minds",
    "set_series": "Sun & Moon"
  },
  {
    "name": "Sneasel",
    "number": "131",
    "rarity": "Common",
    "set_name": "Unified Minds",
    "set_series": "Sun & Moon"
  },
  {
    "name": "Weavile-GX",
    "number": "132",
    "rarity": "Rare Holo GX",
    "set_name": "Unified Minds",
    "set_series": "Sun & Moon"
  },
  {
    "name": "Sableye",
    "number": "133",
    "rarity": "Uncommon",
    "set_name": "Unified Minds",
    "set_series": "Sun & Moon"
  },
  {
    "name": "Drapion",
    "number": "134",
    "rarity": "Rare",
    "set_name": "Unified Minds",
    "set_series": "Sun & Moon"
  },
  {
    "name": "Purrloin",
    "number": "135",
    "rarity": "Common",
    "set_name": "Unified Minds",
    "set_series": "Sun & Moon"
  },
  {
    "name": "Liepard",
    "number": "136",
    "rarity": "Rare",
    "set_name": "Unified Minds",
    "set_series": "Sun & Moon"
  },
  {
    "name": "Scraggy",
    "number": "137",
    "rarity": "Common",
    "set_name": "Unified Minds",
    "set_series": "Sun & Moon"
  },
  {
    "name": "Scrafty",
    "number": "138",
    "rarity": "Rare",
    "set_name": "Unified Minds",
    "set_series": "Sun & Moon"
  },
  {
    "name": "Yveltal",
    "number": "139",
    "rarity": "Rare Holo",
    "set_name": "Unified Minds",
    "set_series": "Sun & Moon"
  },
  {
    "name": "Hoopa",
    "number": "140",
    "rarity": "Rare Holo",
    "set_name": "Unified Minds",
    "set_series": "Sun & Moon"
  },
  {
    "name": "Mawile-GX",
    "number": "141",
    "rarity": "Rare Holo GX",
    "set_name": "Unified Minds",
    "set_series": "Sun & Moon"
  },
  {
    "name": "Escavalier",
    "number": "142",
    "rarity": "Rare",
    "set_name": "Unified Minds",
    "set_series": "Sun & Moon"
  },
  {
    "name": "Cottonee",
    "number": "143",
    "rarity": "Common",
    "set_name": "Unified Minds",
    "set_series": "Sun & Moon"
  },
  {
    "name": "Whimsicott",
    "number": "144",
    "rarity": "Rare",
    "set_name": "Unified Minds",
    "set_series": "Sun & Moon"
  },
  {
    "name": "Dedenne",
    "number": "145",
    "rarity": "Uncommon",
    "set_name": "Unified Minds",
    "set_series": "Sun & Moon"
  },
  {
    "name": "Garchomp & Giratina-GX",
    "number": "146",
    "rarity": "Rare Holo GX",
    "set_name": "Unified Minds",
    "set_series": "Sun & Moon"
  },
  {
    "name": "Dratini",
    "number": "147",
    "rarity": "Common",
    "set_name": "Unified Minds",
    "set_series": "Sun & Moon"
  },
  {
    "name": "Dratini",
    "number": "148",
    "rarity": "Common",
    "set_name": "Unified Minds",
    "set_series": "Sun & Moon"
  },
  {
    "name": "Dragonair",
    "number": "149",
    "rarity": "Uncommon",
    "set_name": "Unified Minds",
    "set_series": "Sun & Moon"
  },
  {
    "name": "Dragonair",
    "number": "150",
    "rarity": "Uncommon",
    "set_name": "Unified Minds",
    "set_series": "Sun & Moon"
  },
  {
    "name": "Dragonite",
    "number": "151",
    "rarity": "Rare",
    "set_name": "Unified Minds",
    "set_series": "Sun & Moon"
  },
  {
    "name": "Dragonite-GX",
    "number": "152",
    "rarity": "Rare Holo GX",
    "set_name": "Unified Minds",
    "set_series": "Sun & Moon"
  },
  {
    "name": "Latias",
    "number": "153",
    "rarity": "Rare",
    "set_name": "Unified Minds",
    "set_series": "Sun & Moon"
  },
  {
    "name": "Axew",
    "number": "154",
    "rarity": "Common",
    "set_name": "Unified Minds",
    "set_series": "Sun & Moon"
  },
  {
    "name": "Fraxure",
    "number": "155",
    "rarity": "Uncommon",
    "set_name": "Unified Minds",
    "set_series": "Sun & Moon"
  },
  {
    "name": "Haxorus",
    "number": "156",
    "rarity": "Rare Holo",
    "set_name": "Unified Minds",
    "set_series": "Sun & Moon"
  },
  {
    "name": "Druddigon",
    "number": "157",
    "rarity": "Common",
    "set_name": "Unified Minds",
    "set_series": "Sun & Moon"
  },
  {
    "name": "Noibat",
    "number": "158",
    "rarity": "Common",
    "set_name": "Unified Minds",
    "set_series": "Sun & Moon"
  },
  {
    "name": "Noivern",
    "number": "159",
    "rarity": "Rare",
    "set_name": "Unified Minds",
    "set_series": "Sun & Moon"
  },
  {
    "name": "Naganadel-GX",
    "number": "160",
    "rarity": "Rare Holo GX",
    "set_name": "Unified Minds",
    "set_series": "Sun & Moon"
  },
  {
    "name": "Lickitung",
    "number": "161",
    "rarity": "Common",
    "set_name": "Unified Minds",
    "set_series": "Sun & Moon"
  },
  {
    "name": "Lickilicky",
    "number": "162",
    "rarity": "Rare",
    "set_name": "Unified Minds",
    "set_series": "Sun & Moon"
  },
  {
    "name": "Kangaskhan",
    "number": "163",
    "rarity": "Rare Holo",
    "set_name": "Unified Minds",
    "set_series": "Sun & Moon"
  },
  {
    "name": "Tauros",
    "number": "164",
    "rarity": "Uncommon",
    "set_name": "Unified Minds",
    "set_series": "Sun & Moon"
  },
  {
    "name": "Hoothoot",
    "number": "165",
    "rarity": "Common",
    "set_name": "Unified Minds",
    "set_series": "Sun & Moon"
  },
  {
    "name": "Noctowl",
    "number": "166",
    "rarity": "Uncommon",
    "set_name": "Unified Minds",
    "set_series": "Sun & Moon"
  },
  {
    "name": "Slakoth",
    "number": "167",
    "rarity": "Common",
    "set_name": "Unified Minds",
    "set_series": "Sun & Moon"
  },
  {
    "name": "Slakoth",
    "number": "168",
    "rarity": "Common",
    "set_name": "Unified Minds",
    "set_series": "Sun & Moon"
  },
  {
    "name": "Vigoroth",
    "number": "169",
    "rarity": "Uncommon",
    "set_name": "Unified Minds",
    "set_series": "Sun & Moon"
  },
  {
    "name": "Slaking",
    "number": "170",
    "rarity": "Rare Holo",
    "set_name": "Unified Minds",
    "set_series": "Sun & Moon"
  },
  {
    "name": "Bidoof",
    "number": "171",
    "rarity": "Common",
    "set_name": "Unified Minds",
    "set_series": "Sun & Moon"
  },
  {
    "name": "Bibarel",
    "number": "172",
    "rarity": "Uncommon",
    "set_name": "Unified Minds",
    "set_series": "Sun & Moon"
  },
  {
    "name": "Munchlax",
    "number": "173",
    "rarity": "Uncommon",
    "set_name": "Unified Minds",
    "set_series": "Sun & Moon"
  },
  {
    "name": "Pidove",
    "number": "174",
    "rarity": "Common",
    "set_name": "Unified Minds",
    "set_series": "Sun & Moon"
  },
  {
    "name": "Tranquill",
    "number": "175",
    "rarity": "Uncommon",
    "set_name": "Unified Minds",
    "set_series": "Sun & Moon"
  },
  {
    "name": "Unfezant",
    "number": "176",
    "rarity": "Rare",
    "set_name": "Unified Minds",
    "set_series": "Sun & Moon"
  },
  {
    "name": "Audino",
    "number": "177",
    "rarity": "Uncommon",
    "set_name": "Unified Minds",
    "set_series": "Sun & Moon"
  },
  {
    "name": "Tornadus",
    "number": "178",
    "rarity": "Uncommon",
    "set_name": "Unified Minds",
    "set_series": "Sun & Moon"
  },
  {
    "name": "Fletchling",
    "number": "179",
    "rarity": "Common",
    "set_name": "Unified Minds",
    "set_series": "Sun & Moon"
  },
  {
    "name": "Yungoos",
    "number": "180",
    "rarity": "Common",
    "set_name": "Unified Minds",
    "set_series": "Sun & Moon"
  },
  {
    "name": "Gumshoos",
    "number": "181",
    "rarity": "Rare",
    "set_name": "Unified Minds",
    "set_series": "Sun & Moon"
  },
  {
    "name": "Oranguru",
    "number": "182",
    "rarity": "Uncommon",
    "set_name": "Unified Minds",
    "set_series": "Sun & Moon"
  },
  {
    "name": "Type: Null",
    "number": "183",
    "rarity": "Uncommon",
    "set_name": "Unified Minds",
    "set_series": "Sun & Moon"
  },
  {
    "name": "Silvally",
    "number": "184",
    "rarity": "Rare Holo",
    "set_name": "Unified Minds",
    "set_series": "Sun & Moon"
  },
  {
    "name": "Komala",
    "number": "185",
    "rarity": "Uncommon",
    "set_name": "Unified Minds",
    "set_series": "Sun & Moon"
  },
  {
    "name": "Blaine's Quiz Show",
    "number": "186",
    "rarity": "Uncommon",
    "set_name": "Unified Minds",
    "set_series": "Sun & Moon"
  },
  {
    "name": "Blizzard Town",
    "number": "187",
    "rarity": "Uncommon",
    "set_name": "Unified Minds",
    "set_series": "Sun & Moon"
  },
  {
    "name": "Blue's Tactics",
    "number": "188",
    "rarity": "Uncommon",
    "set_name": "Unified Minds",
    "set_series": "Sun & Moon"
  },
  {
    "name": "Bug Catcher",
    "number": "189",
    "rarity": "Uncommon",
    "set_name": "Unified Minds",
    "set_series": "Sun & Moon"
  },
  {
    "name": "Channeler",
    "number": "190",
    "rarity": "Uncommon",
    "set_name": "Unified Minds",
    "set_series": "Sun & Moon"
  },
  {
    "name": "Cherish Ball",
    "number": "191",
    "rarity": "Uncommon",
    "set_name": "Unified Minds",
    "set_series": "Sun & Moon"
  },
  {
    "name": "Cherish Ball",
    "number": "191a",
    "rarity": "Uncommon",
    "set_name": "Unified Minds",
    "set_series": "Sun & Moon"
  },
  {
    "name": "Coach Trainer",
    "number": "192",
    "rarity": "Uncommon",
    "set_name": "Unified Minds",
    "set_series": "Sun & Moon"
  },
  {
    "name": "Dark City",
    "number": "193",
    "rarity": "Uncommon",
    "set_name": "Unified Minds",
    "set_series": "Sun & Moon"
  },
  {
    "name": "Ear-Ringing Bell",
    "number": "194",
    "rarity": "Uncommon",
    "set_name": "Unified Minds",
    "set_series": "Sun & Moon"
  },
  {
    "name": "Flyinium Z: Air Slash",
    "number": "195",
    "rarity": "Uncommon",
    "set_name": "Unified Minds",
    "set_series": "Sun & Moon"
  },
  {
    "name": "Giant Bomb",
    "number": "196",
    "rarity": "Uncommon",
    "set_name": "Unified Minds",
    "set_series": "Sun & Moon"
  },
  {
    "name": "Giant Hearth",
    "number": "197",
    "rarity": "Uncommon",
    "set_name": "Unified Minds",
    "set_series": "Sun & Moon"
  },
  {
    "name": "Great Potion",
    "number": "198",
    "rarity": "Uncommon",
    "set_name": "Unified Minds",
    "set_series": "Sun & Moon"
  },
  {
    "name": "Grimsley",
    "number": "199",
    "rarity": "Uncommon",
    "set_name": "Unified Minds",
    "set_series": "Sun & Moon"
  },
  {
    "name": "Hapu",
    "number": "200",
    "rarity": "Uncommon",
    "set_name": "Unified Minds",
    "set_series": "Sun & Moon"
  },
  {
    "name": "Karate Belt",
    "number": "201",
    "rarity": "Uncommon",
    "set_name": "Unified Minds",
    "set_series": "Sun & Moon"
  },
  {
    "name": "Misty's Favor",
    "number": "202",
    "rarity": "Uncommon",
    "set_name": "Unified Minds",
    "set_series": "Sun & Moon"
  },
  {
    "name": "Normalium Z: Tackle",
    "number": "203",
    "rarity": "Uncommon",
    "set_name": "Unified Minds",
    "set_series": "Sun & Moon"
  },
  {
    "name": "Pok\u00e9 Maniac",
    "number": "204",
    "rarity": "Uncommon",
    "set_name": "Unified Minds",
    "set_series": "Sun & Moon"
  },
  {
    "name": "Pok\u00e9mon Research Lab",
    "number": "205",
    "rarity": "Uncommon",
    "set_name": "Unified Minds",
    "set_series": "Sun & Moon"
  },
  {
    "name": "Reset Stamp",
    "number": "206",
    "rarity": "Uncommon",
    "set_name": "Unified Minds",
    "set_series": "Sun & Moon"
  },
  {
    "name": "Reset Stamp",
    "number": "206a",
    "rarity": "Uncommon",
    "set_name": "Unified Minds",
    "set_series": "Sun & Moon"
  },
  {
    "name": "Slumbering Forest",
    "number": "207",
    "rarity": "Uncommon",
    "set_name": "Unified Minds",
    "set_series": "Sun & Moon"
  },
  {
    "name": "Stadium Nav",
    "number": "208",
    "rarity": "Uncommon",
    "set_name": "Unified Minds",
    "set_series": "Sun & Moon"
  },
  {
    "name": "Tag Switch",
    "number": "209",
    "rarity": "Uncommon",
    "set_name": "Unified Minds",
    "set_series": "Sun & Moon"
  },
  {
    "name": "Unidentified Fossil",
    "number": "210",
    "rarity": "Uncommon",
    "set_name": "Unified Minds",
    "set_series": "Sun & Moon"
  },
  {
    "name": "U-Turn Board",
    "number": "211",
    "rarity": "Uncommon",
    "set_name": "Unified Minds",
    "set_series": "Sun & Moon"
  },
  {
    "name": "Recycle Energy",
    "number": "212",
    "rarity": "Uncommon",
    "set_name": "Unified Minds",
    "set_series": "Sun & Moon"
  },
  {
    "name": "Weakness Guard Energy",
    "number": "213",
    "rarity": "Uncommon",
    "set_name": "Unified Minds",
    "set_series": "Sun & Moon"
  },
  {
    "name": "Rowlet & Alolan Exeggutor-GX",
    "number": "214",
    "rarity": "Rare Ultra",
    "set_name": "Unified Minds",
    "set_series": "Sun & Moon"
  },
  {
    "name": "Rowlet & Alolan Exeggutor-GX",
    "number": "215",
    "rarity": "Rare Ultra",
    "set_name": "Unified Minds",
    "set_series": "Sun & Moon"
  },
  {
    "name": "Heatran-GX",
    "number": "216",
    "rarity": "Rare Ultra",
    "set_name": "Unified Minds",
    "set_series": "Sun & Moon"
  },
  {
    "name": "Slowpoke & Psyduck-GX",
    "number": "217",
    "rarity": "Rare Ultra",
    "set_name": "Unified Minds",
    "set_series": "Sun & Moon"
  },
  {
    "name": "Slowpoke & Psyduck-GX",
    "number": "218",
    "rarity": "Rare Ultra",
    "set_name": "Unified Minds",
    "set_series": "Sun & Moon"
  },
  {
    "name": "Keldeo-GX",
    "number": "219",
    "rarity": "Rare Ultra",
    "set_name": "Unified Minds",
    "set_series": "Sun & Moon"
  },
  {
    "name": "Raichu & Alolan Raichu-GX",
    "number": "220",
    "rarity": "Rare Ultra",
    "set_name": "Unified Minds",
    "set_series": "Sun & Moon"
  },
  {
    "name": "Raichu & Alolan Raichu-GX",
    "number": "221",
    "rarity": "Rare Ultra",
    "set_name": "Unified Minds",
    "set_series": "Sun & Moon"
  },
  {
    "name": "Mewtwo & Mew-GX",
    "number": "222",
    "rarity": "Rare Ultra",
    "set_name": "Unified Minds",
    "set_series": "Sun & Moon"
  },
  {
    "name": "Latios-GX",
    "number": "223",
    "rarity": "Rare Ultra",
    "set_name": "Unified Minds",
    "set_series": "Sun & Moon"
  },
  {
    "name": "Aerodactyl-GX",
    "number": "224",
    "rarity": "Rare Ultra",
    "set_name": "Unified Minds",
    "set_series": "Sun & Moon"
  },
  {
    "name": "Mega Sableye & Tyranitar-GX",
    "number": "225",
    "rarity": "Rare Ultra",
    "set_name": "Unified Minds",
    "set_series": "Sun & Moon"
  },
  {
    "name": "Mega Sableye & Tyranitar-GX",
    "number": "226",
    "rarity": "Rare Ultra",
    "set_name": "Unified Minds",
    "set_series": "Sun & Moon"
  },
  {
    "name": "Mawile-GX",
    "number": "227",
    "rarity": "Rare Ultra",
    "set_name": "Unified Minds",
    "set_series": "Sun & Moon"
  },
  {
    "name": "Garchomp & Giratina-GX",
    "number": "228",
    "rarity": "Rare Ultra",
    "set_name": "Unified Minds",
    "set_series": "Sun & Moon"
  },
  {
    "name": "Dragonite-GX",
    "number": "229",
    "rarity": "Rare Ultra",
    "set_name": "Unified Minds",
    "set_series": "Sun & Moon"
  },
  {
    "name": "Naganadel-GX",
    "number": "230",
    "rarity": "Rare Ultra",
    "set_name": "Unified Minds",
    "set_series": "Sun & Moon"
  },
  {
    "name": "Blue's Tactics",
    "number": "231",
    "rarity": "Rare Ultra",
    "set_name": "Unified Minds",
    "set_series": "Sun & Moon"
  },
  {
    "name": "Channeler",
    "number": "232",
    "rarity": "Rare Ultra",
    "set_name": "Unified Minds",
    "set_series": "Sun & Moon"
  },
  {
    "name": "Coach Trainer",
    "number": "233",
    "rarity": "Rare Ultra",
    "set_name": "Unified Minds",
    "set_series": "Sun & Moon"
  },
  {
    "name": "Grimsley",
    "number": "234",
    "rarity": "Rare Ultra",
    "set_name": "Unified Minds",
    "set_series": "Sun & Moon"
  },
  {
    "name": "Misty's Favor",
    "number": "235",
    "rarity": "Rare Ultra",
    "set_name": "Unified Minds",
    "set_series": "Sun & Moon"
  },
  {
    "name": "Pok\u00e9 Maniac",
    "number": "236",
    "rarity": "Rare Ultra",
    "set_name": "Unified Minds",
    "set_series": "Sun & Moon"
  },
  {
    "name": "Rowlet & Alolan Exeggutor-GX",
    "number": "237",
    "rarity": "Rare Rainbow",
    "set_name": "Unified Minds",
    "set_series": "Sun & Moon"
  },
  {
    "name": "Heatran-GX",
    "number": "238",
    "rarity": "Rare Rainbow",
    "set_name": "Unified Minds",
    "set_series": "Sun & Moon"
  },
  {
    "name": "Slowpoke & Psyduck-GX",
    "number": "239",
    "rarity": "Rare Rainbow",
    "set_name": "Unified Minds",
    "set_series": "Sun & Moon"
  },
  {
    "name": "Keldeo-GX",
    "number": "240",
    "rarity": "Rare Rainbow",
    "set_name": "Unified Minds",
    "set_series": "Sun & Moon"
  },
  {
    "name": "Raichu & Alolan Raichu-GX",
    "number": "241",
    "rarity": "Rare Rainbow",
    "set_name": "Unified Minds",
    "set_series": "Sun & Moon"
  },
  {
    "name": "Mewtwo & Mew-GX",
    "number": "242",
    "rarity": "Rare Rainbow",
    "set_name": "Unified Minds",
    "set_series": "Sun & Moon"
  },
  {
    "name": "Latios-GX",
    "number": "243",
    "rarity": "Rare Rainbow",
    "set_name": "Unified Minds",
    "set_series": "Sun & Moon"
  },
  {
    "name": "Aerodactyl-GX",
    "number": "244",
    "rarity": "Rare Rainbow",
    "set_name": "Unified Minds",
    "set_series": "Sun & Moon"
  },
  {
    "name": "Mega Sableye & Tyranitar-GX",
    "number": "245",
    "rarity": "Rare Rainbow",
    "set_name": "Unified Minds",
    "set_series": "Sun & Moon"
  },
  {
    "name": "Mawile-GX",
    "number": "246",
    "rarity": "Rare Rainbow",
    "set_name": "Unified Minds",
    "set_series": "Sun & Moon"
  },
  {
    "name": "Garchomp & Giratina-GX",
    "number": "247",
    "rarity": "Rare Rainbow",
    "set_name": "Unified Minds",
    "set_series": "Sun & Moon"
  },
  {
    "name": "Dragonite-GX",
    "number": "248",
    "rarity": "Rare Rainbow",
    "set_name": "Unified Minds",
    "set_series": "Sun & Moon"
  }
]