[
  {
    "name": "Bellsprout",
    "number": "1",
    "rarity": "Common",
    "set_name": "Celestial Storm",
    "set_series": "Sun & Moon"
  },
  {
    "name": "Weepinbell",
    "number": "2",
    "rarity": "Uncommon",
    "set_name": "Celestial Storm",
    "set_series": "Sun & Moon"
  },
  {
    "name": "Victreebel",
    "number": "3",
    "rarity": "Rare Holo",
    "set_name": "Celestial Storm",
    "set_series": "Sun & Moon"
  },
  {
    "name": "Scyther",
    "number": "4",
    "rarity": "Uncommon",
    "set_name": "Celestial Storm",
    "set_series": "Sun & Moon"
  },
  {
    "name": "Spinarak",
    "number": "5",
    "rarity": "Common",
    "set_name": "Celestial Storm",
    "set_series": "Sun & Moon"
  },
  {
    "name": "Ariados",
    "number": "6",
    "rarity": "Rare Holo",
    "set_name": "Celestial Storm",
    "set_series": "Sun & Moon"
  },
  {
    "name": "Treecko",
    "number": "7",
    "rarity": "Common",
    "set_name": "Celestial Storm",
    "set_series": "Sun & Moon"
  },
  {
    "name": "Treecko",
    "number": "8",
    "rarity": "Common",
    "set_name": "Celestial Storm",
    "set_series": "Sun & Moon"
  },
  {
    "name": "Grovyle",
    "number": "9",
    "rarity": "Uncommon",
    "set_name": "Celestial Storm",
    "set_series": "Sun & Moon"
  },
  {
    "name": "Sceptile",
    "number": "10",
    "rarity": "Rare",
    "set_name": "Celestial Storm",
    "set_series": "Sun & Moon"
  },
  {
    "name": "Sceptile",
    "number": "10a",
    "rarity": "Rare Holo",
    "set_name": "Celestial Storm",
    "set_series": "Sun & Moon"
  },
  {
    "name": "Seedot",
    "number": "11",
    "rarity": "Common",
    "set_name": "Celestial Storm",
    "set_series": "Sun & Moon"
  },
  {
    "name": "Seedot",
    "number": "12",
    "rarity": "Common",
    "set_name": "Celestial Storm",
    "set_series": "Sun & Moon"
  },
  {
    "name": "Nuzleaf",
    "number": "13",
    "rarity": "Uncommon",
    "set_name": "Celestial Storm",
    "set_series": "Sun & Moon"
  },
  {
    "name": "Shiftry-GX",
    "number": "14",
    "rarity": "Rare Holo GX",
    "set_name": "Celestial Storm",
    "set_series": "Sun & Moon"
  },
  {
    "name": "Surskit",
    "number": "15",
    "rarity": "Common",
    "set_name": "Celestial Storm",
    "set_series": "Sun & Moon"
  },
  {
    "name": "Masquerain",
    "number": "16",
    "rarity": "Uncommon",
    "set_name": "Celestial Storm",
    "set_series": "Sun & Moon"
  },
  {
    "name": "Volbeat",
    "number": "17",
    "rarity": "Uncommon",
    "set_name": "Celestial Storm",
    "set_series": "Sun & Moon"
  },
  {
    "name": "Illumise",
    "number": "18",
    "rarity": "Uncommon",
    "set_name": "Celestial Storm",
    "set_series": "Sun & Moon"
  },
  {
    "name": "Cacnea",
    "number": "19",
    "rarity": "Common",
    "set_name": "Celestial Storm",
    "set_series": "Sun & Moon"
  },
  {
    "name": "Cacturne",
    "number": "20",
    "rarity": "Uncommon",
    "set_name": "Celestial Storm",
    "set_series": "Sun & Moon"
  },
  {
    "name": "Tropius",
    "number": "21",
    "rarity": "Uncommon",
    "set_name": "Celestial Storm",
    "set_series": "Sun & Moon"
  },
  {
    "name": "Dhelmise",
    "number": "22",
    "rarity": "Rare",
    "set_name": "Celestial Storm",
    "set_series": "Sun & Moon"
  },
  {
    "name": "Slugma",
    "number": "23",
    "rarity": "Common",
    "set_name": "Celestial Storm",
    "set_series": "Sun & Moon"
  },
  {
    "name": "Magcargo",
    "number": "24",
    "rarity": "Rare",
    "set_name": "Celestial Storm",
    "set_series": "Sun & Moon"
  },
  {
    "name": "Torchic",
    "number": "25",
    "rarity": "Common",
    "set_name": "Celestial Storm",
    "set_series": "Sun & Moon"
  },
  {
    "name": "Torchic",
    "number": "26",
    "rarity": "Common",
    "set_name": "Celestial Storm",
    "set_series": "Sun & Moon"
  },
  {
    "name": "Combusken",
    "number": "27",
    "rarity": "Uncommon",
    "set_name": "Celestial Storm",
    "set_series": "Sun & Moon"
  },
  {
    "name": "Blaziken-GX",
    "number": "28",
    "rarity": "Rare Holo GX",
    "set_name": "Celestial Storm",
    "set_series": "Sun & Moon"
  },
  {
    "name": "Torkoal",
    "number": "29",
    "rarity": "Uncommon",
    "set_name": "Celestial Storm",
    "set_series": "Sun & Moon"
  },
  {
    "name": "Oricorio",
    "number": "30",
    "rarity": "Uncommon",
    "set_name": "Celestial Storm",
    "set_series": "Sun & Moon"
  },
  {
    "name": "Articuno-GX",
    "number": "31",
    "rarity": "Rare Holo GX",
    "set_name": "Celestial Storm",
    "set_series": "Sun & Moon"
  },
  {
    "name": "Mudkip",
    "number": "32",
    "rarity": "Common",
    "set_name": "Celestial Storm",
    "set_series": "Sun & Moon"
  },
  {
    "name": "Mudkip",
    "number": "33",
    "rarity": "Common",
    "set_name": "Celestial Storm",
    "set_series": "Sun & Moon"
  },
  {
    "name": "Marshtomp",
    "number": "34",
    "rarity": "Uncommon",
    "set_name": "Celestial Storm",
    "set_series": "Sun & Moon"
  },
  {
    "name": "Swampert",
    "number": "35",
    "rarity": "Rare",
    "set_name": "Celestial Storm",
    "set_series": "Sun & Moon"
  },
  {
    "name": "Lotad",
    "number": "36",
    "rarity": "Common",
    "set_name": "Celestial Storm",
    "set_series": "Sun & Moon"
  },
  {
    "name": "Lombre",
    "number": "37",
    "rarity": "Uncommon",
    "set_name": "Celestial Storm",
    "set_series": "Sun & Moon"
  },
  {
    "name": "Ludicolo",
    "number": "38",
    "rarity": "Rare Holo",
    "set_name": "Celestial Storm",
    "set_series": "Sun & Moon"
  },
  {
    "name": "Wailmer",
    "number": "39",
    "rarity": "Common",
    "set_name": "Celestial Storm",
    "set_series": "Sun & Moon"
  },
  {
    "name": "Wailord",
    "number": "40",
    "rarity": "Rare",
    "set_name": "Celestial Storm",
    "set_series": "Sun & Moon"
  },
  {
    "name": "Clamperl",
    "number": "41",
    "rarity": "Common",
    "set_name": "Celestial Storm",
    "set_series": "Sun & Moon"
  },
  {
    "name": "Huntail",
    "number": "42",
    "rarity": "Uncommon",
    "set_name": "Celestial Storm",
    "set_series": "Sun & Moon"
  },
  {
    "name": "Gorebyss",
    "number": "43",
    "rarity": "Uncommon",
    "set_name": "Celestial Storm",
    "set_series": "Sun & Moon"
  },
  {
    "name": "Luvdisc",
    "number": "44",
    "rarity": "Common",
    "set_name": "Celestial Storm",
    "set_series": "Sun & Moon"
  },
  {
    "name": "Regice",
    "number": "45",
    "rarity": "Rare",
    "set_name": "Celestial Storm",
    "set_series": "Sun & Moon"
  },
  {
    "name": "Kyogre",
    "number": "46",
    "rarity": "Rare Holo",
    "set_name": "Celestial Storm",
    "set_series": "Sun & Moon"
  },
  {
    "name": "Voltorb",
    "number": "47",
    "rarity": "Common",
    "set_name": "Celestial Storm",
    "set_series": "Sun & Moon"
  },
  {
    "name": "Electrode-GX",
    "number": "48",
    "rarity": "Rare Holo GX",
    "set_name": "Celestial Storm",
    "set_series": "Sun & Moon"
  },
  {
    "name": "Chinchou",
    "number": "49",
    "rarity": "Common",
    "set_name": "Celestial Storm",
    "set_series": "Sun & Moon"
  },
  {
    "name": "Lanturn",
    "number": "50",
    "rarity": "Uncommon",
    "set_name": "Celestial Storm",
    "set_series": "Sun & Moon"
  },
  {
    "name": "Electrike",
    "number": "51",
    "rarity": "Common",
    "set_name": "Celestial Storm",
    "set_series": "Sun & Moon"
  },
  {
    "name": "Manectric",
    "number": "52",
    "rarity": "Rare",
    "set_name": "Celestial Storm",
    "set_series": "Sun & Moon"
  },
  {
    "name": "Plusle",
    "number": "53",
    "rarity": "Uncommon",
    "set_name": "Celestial Storm",
    "set_series": "Sun & Moon"
  },
  {
    "name": "Minun",
    "number": "54",
    "rarity": "Uncommon",
    "set_name": "Celestial Storm",
    "set_series": "Sun & Moon"
  },
  {
    "name": "Oricorio",
    "number": "55",
    "rarity": "Uncommon",
    "set_name": "Celestial Storm",
    "set_series": "Sun & Moon"
  },
  {
    "name": "Mr. Mime-GX",
    "number": "56",
    "rarity": "Rare Holo GX",
    "set_name": "Celestial Storm",
    "set_series": "Sun & Moon"
  },
  {
    "name": "Gulpin",
    "number": "57",
    "rarity": "Common",
    "set_name": "Celestial Storm",
    "set_series": "Sun & Moon"
  },
  {
    "name": "Swalot",
    "number": "58",
    "rarity": "Uncommon",
    "set_name": "Celestial Storm",
    "set_series": "Sun & Moon"
  },
  {
    "name": "Spoink",
    "number": "59",
    "rarity": "Common",
    "set_name": "Celestial Storm",
    "set_series": "Sun & Moon"
  },
  {
    "name": "Grumpig",
    "number": "60",
    "rarity": "Rare",
    "set_name": "Celestial Storm",
    "set_series": "Sun & Moon"
  },
  {
    "name": "Lunatone",
    "number": "61",
    "rarity": "Rare Holo",
    "set_name": "Celestial Storm",
    "set_series": "Sun & Moon"
  },
  {
    "name": "Solrock",
    "number": "62",
    "rarity": "Uncommon",
    "set_name": "Celestial Storm",
    "set_series": "Sun & Moon"
  },
  {
    "name": "Shuppet",
    "number": "63",
    "rarity": "Common",
    "set_name": "Celestial Storm",
    "set_series": "Sun & Moon"
  },
  {
    "name": "Shuppet",
    "number": "64",
    "rarity": "Common",
    "set_name": "Celestial Storm",
    "set_series": "Sun & Moon"
  },
  {
    "name": "Banette",
    "number": "65",
    "rarity": "Rare",
    "set_name": "Celestial Storm",
    "set_series": "Sun & Moon"
  },
  {
    "name": "Banette-GX",
    "number": "66",
    "rarity": "Rare Holo GX",
    "set_name": "Celestial Storm",
    "set_series": "Sun & Moon"
  },
  {
    "name": "Deoxys",
    "number": "67",
    "rarity": "Rare Holo",
    "set_name": "Celestial Storm",
    "set_series": "Sun & Moon"
  },
  {
    "name": "Deoxys",
    "number": "68",
    "rarity": "Rare",
    "set_name": "Celestial Storm",
    "set_series": "Sun & Moon"
  },
  {
    "name": "Deoxys",
    "number": "69",
    "rarity": "Rare",
    "set_name": "Celestial Storm",
    "set_series": "Sun & Moon"
  },
  {
    "name": "Lunala",
    "number": "70",
    "rarity": "Rare Holo",
    "set_name": "Celestial Storm",
    "set_series": "Sun & Moon"
  },
  {
    "name": "Onix",
    "number": "71",
    "rarity": "Common",
    "set_name": "Celestial Storm",
    "set_series": "Sun & Moon"
  },
  {
    "name": "Phanpy",
    "number": "72",
    "rarity": "Common",
    "set_name": "Celestial Storm",
    "set_series": "Sun & Moon"
  },
  {
    "name": "Donphan",
    "number": "73",
    "rarity": "Uncommon",
    "set_name": "Celestial Storm",
    "set_series": "Sun & Moon"
  },
  {
    "name": "Larvitar",
    "number": "74",
    "rarity": "Common",
    "set_name": "Celestial Storm",
    "set_series": "Sun & Moon"
  },
  {
    "name": "Pupitar",
    "number": "75",
    "rarity": "Uncommon",
    "set_name": "Celestial Storm",
    "set_series": "Sun & Moon"
  },
  {
    "name": "Meditite",
    "number": "76",
    "rarity": "Common",
    "set_name": "Celestial Storm",
    "set_series": "Sun & Moon"
  },
  {
    "name": "Medicham",
    "number": "77",
    "rarity": "Rare",
    "set_name": "Celestial Storm",
    "set_series": "Sun & Moon"
  },
  {
    "name": "Baltoy",
    "number": "78",
    "rarity": "Common",
    "set_name": "Celestial Storm",
    "set_series": "Sun & Moon"
  },
  {
    "name": "Claydol",
    "number": "79",
    "rarity": "Rare",
    "set_name": "Celestial Storm",
    "set_series": "Sun & Moon"
  },
  {
    "name": "Regirock",
    "number": "80",
    "rarity": "Rare",
    "set_name": "Celestial Storm",
    "set_series": "Sun & Moon"
  },
  {
    "name": "Groudon",
    "number": "81",
    "rarity": "Rare Holo",
    "set_name": "Celestial Storm",
    "set_series": "Sun & Moon"
  },
  {
    "name": "Palossand-GX",
    "number": "82",
    "rarity": "Rare Holo GX",
    "set_name": "Celestial Storm",
    "set_series": "Sun & Moon"
  },
  {
    "name": "Minior",
    "number": "83",
    "rarity": "Uncommon",
    "set_name": "Celestial Storm",
    "set_series": "Sun & Moon"
  },
  {
    "name": "Alolan Rattata",
    "number": "84",
    "rarity": "Common",
    "set_name": "Celestial Storm",
    "set_series": "Sun & Moon"
  },
  {
    "name": "Alolan Raticate-GX",
    "number": "85",
    "rarity": "Rare Holo GX",
    "set_name": "Celestial Storm",
    "set_series": "Sun & Moon"
  },
  {
    "name": "Sneasel",
    "number": "86",
    "rarity": "Common",
    "set_name": "Celestial Storm",
    "set_series": "Sun & Moon"
  },
  {
    "name": "Tyranitar",
    "number": "87",
    "rarity": "Rare Holo",
    "set_name": "Celestial Storm",
    "set_series": "Sun & Moon"
  },
  {
    "name": "Sableye",
    "number": "88",
    "rarity": "Uncommon",
    "set_name": "Celestial Storm",
    "set_series": "Sun & Moon"
  },
  {
    "name": "Steelix",
    "number": "89",
    "rarity": "Rare Holo",
    "set_name": "Celestial Storm",
    "set_series": "Sun & Moon"
  },
  {
    "name": "Scizor-GX",
    "number": "90",
    "rarity": "Rare Holo GX",
    "set_name": "Celestial Storm",
    "set_series": "Sun & Moon"
  },
  {
    "name": "Mawile",
    "number": "91",
    "rarity": "Uncommon",
    "set_name": "Celestial Storm",
    "set_series": "Sun & Moon"
  },
  {
    "name": "Beldum",
    "number": "92",
    "rarity": "Common",
    "set_name": "Celestial Storm",
    "set_series": "Sun & Moon"
  },
  {
    "name": "Beldum",
    "number": "93",
    "rarity": "Common",
    "set_name": "Celestial Storm",
    "set_series": "Sun & Moon"
  },
  {
    "name": "Metang",
    "number": "94",
    "rarity": "Uncommon",
    "set_name": "Celestial Storm",
    "set_series": "Sun & Moon"
  },
  {
    "name": "Metagross",
    "number": "95",
    "rarity": "Rare Holo",
    "set_name": "Celestial Storm",
    "set_series": "Sun & Moon"
  },
  {
    "name": "Registeel",
    "number": "96",
    "rarity": "Rare",
    "set_name": "Celestial Storm",
    "set_series": "Sun & Moon"
  },
  {
    "name": "Jirachi \u25c7",
    "number": "97",
    "rarity": "Rare Prism Star",
    "set_name": "Celestial Storm",
    "set_series": "Sun & Moon"
  },
  {
    "name": "Heatran",
    "number": "98",
    "rarity": "Rare Holo",
    "set_name": "Celestial Storm",
    "set_series": "Sun & Moon"
  },
  {
    "name": "Solgaleo",
    "number": "99",
    "rarity": "Rare Holo",
    "set_name": "Celestial Storm",
    "set_series": "Sun & Moon"
  },
  {
    "name": "Celesteela",
    "number": "100",
    "rarity": "Rare Holo",
    "set_name": "Celestial Storm",
    "set_series": "Sun & Moon"
  },
  {
    "name": "Kartana",
    "number": "101",
    "rarity": "Rare",
    "set_name": "Celestial Storm",
    "set_series": "Sun & Moon"
  },
  {
    "name": "Stakataka-GX",
    "number": "102",
    "rarity": "Rare Holo GX",
    "set_name": "Celestial Storm",
    "set_series": "Sun & Moon"
  },
  {
    "name": "Bagon",
    "number": "103",
    "rarity": "Common",
    "set_name": "Celestial Storm",
    "set_series": "Sun & Moon"
  },
  {
    "name": "Bagon",
    "number": "104",
    "rarity": "Common",
    "set_name": "Celestial Storm",
    "set_series": "Sun & Moon"
  },
  {
    "name": "Shelgon",
    "number": "105",
    "rarity": "Uncommon",
    "set_name": "Celestial Storm",
    "set_series": "Sun & Moon"
  },
  {
    "name": "Salamence",
    "number": "106",
    "rarity": "Rare Holo",
    "set_name": "Celestial Storm",
    "set_series": "Sun & Moon"
  },
  {
    "name": "Latias \u25c7",
    "number": "107",
    "rarity": "Rare Prism Star",
    "set_name": "Celestial Storm",
    "set_series": "Sun & Moon"
  },
  {
    "name": "Latios \u25c7",
    "number": "108",
    "rarity": "Rare Prism Star",
    "set_name": "Celestial Storm",
    "set_series": "Sun & Moon"
  },
  {
    "name": "Rayquaza-GX",
    "number": "109",
    "rarity": "Rare Holo GX",
    "set_name": "Celestial Storm",
    "set_series": "Sun & Moon"
  },
  {
    "name": "Dunsparce",
    "number": "110",
    "rarity": "Uncommon",
    "set_name": "Celestial Storm",
    "set_series": "Sun & Moon"
  },
  {
    "name": "Wingull",
    "number": "111",
    "rarity": "Common",
    "set_name": "Celestial Storm",
    "set_series": "Sun & Moon"
  },
  {
    "name": "Pelipper",
    "number": "112",
    "rarity": "Uncommon",
    "set_name": "Celestial Storm",
    "set_series": "Sun & Moon"
  },
  {
    "name": "Slakoth",
    "number": "113",
    "rarity": "Common",
    "set_name": "Celestial Storm",
    "set_series": "Sun & Moon"
  },
  {
    "name": "Vigoroth",
    "number": "114",
    "rarity": "Uncommon",
    "set_name": "Celestial Storm",
    "set_series": "Sun & Moon"
  },
  {
    "name": "Slaking",
    "number": "115",
    "rarity": "Rare Holo",
    "set_name": "Celestial Storm",
    "set_series": "Sun & Moon"
  },
  {
    "name": "Whismur",
    "number": "116",
    "rarity": "Common",
    "set_name": "Celestial Storm",
    "set_series": "Sun & Moon"
  },
  {
    "name": "Whismur",
    "number": "117",
    "rarity": "Common",
    "set_name": "Celestial Storm",
    "set_series": "Sun & Moon"
  },
  {
    "name": "Loudred",
    "number": "118",
    "rarity": "Uncommon",
    "set_name": "Celestial Storm",
    "set_series": "Sun & Moon"
  },
  {
    "name": "Exploud",
    "number": "119",
    "rarity": "Rare",
    "set_name": "Celestial Storm",
    "set_series": "Sun & Moon"
  },
  {
    "name": "Skitty",
    "number": "120",
    "rarity": "Common",
    "set_name": "Celestial Storm",
    "set_series": "Sun & Moon"
  },
  {
    "name": "Delcatty",
    "number": "121",
    "rarity": "Rare Holo",
    "set_name": "Celestial Storm",
    "set_series": "Sun & Moon"
  },
  {
    "name": "Kecleon",
    "number": "122",
    "rarity": "Uncommon",
    "set_name": "Celestial Storm",
    "set_series": "Sun & Moon"
  },
  {
    "name": "Acro Bike",
    "number": "123",
    "rarity": "Uncommon",
    "set_name": "Celestial Storm",
    "set_series": "Sun & Moon"
  },
  {
    "name": "Acro Bike",
    "number": "123a",
    "rarity": "Uncommon",
    "set_name": "Celestial Storm",
    "set_series": "Sun & Moon"
  },
  {
    "name": "Apricorn Maker",
    "number": "124",
    "rarity": "Uncommon",
    "set_name": "Celestial Storm",
    "set_series": "Sun & Moon"
  },
  {
    "name": "Beast Ball",
    "number": "125",
    "rarity": "Uncommon",
    "set_name": "Celestial Storm",
    "set_series": "Sun & Moon"
  },
  {
    "name": "Bill's Maintenance",
    "number": "126",
    "rarity": "Uncommon",
    "set_name": "Celestial Storm",
    "set_series": "Sun & Moon"
  },
  {
    "name": "Copycat",
    "number": "127",
    "rarity": "Uncommon",
    "set_name": "Celestial Storm",
    "set_series": "Sun & Moon"
  },
  {
    "name": "Energy Recycle System",
    "number": "128",
    "rarity": "Uncommon",
    "set_name": "Celestial Storm",
    "set_series": "Sun & Moon"
  },
  {
    "name": "Energy Switch",
    "number": "129",
    "rarity": "Uncommon",
    "set_name": "Celestial Storm",
    "set_series": "Sun & Moon"
  },
  {
    "name": "Fisherman",
    "number": "130",
    "rarity": "Uncommon",
    "set_name": "Celestial Storm",
    "set_series": "Sun & Moon"
  },
  {
    "name": "Friend Ball",
    "number": "131",
    "rarity": "Uncommon",
    "set_name": "Celestial Storm",
    "set_series": "Sun & Moon"
  },
  {
    "name": "Hau",
    "number": "132",
    "rarity": "Uncommon",
    "set_name": "Celestial Storm",
    "set_series": "Sun & Moon"
  },
  {
    "name": "Hiker",
    "number": "133",
    "rarity": "Uncommon",
    "set_name": "Celestial Storm",
    "set_series": "Sun & Moon"
  },
  {
    "name": "Hustle Belt",
    "number": "134",
    "rarity": "Uncommon",
    "set_name": "Celestial Storm",
    "set_series": "Sun & Moon"
  },
  {
    "name": "Last Chance Potion",
    "number": "135",
    "rarity": "Uncommon",
    "set_name": "Celestial Storm",
    "set_series": "Sun & Moon"
  },
  {
    "name": "Life Herb",
    "number": "136",
    "rarity": "Uncommon",
    "set_name": "Celestial Storm",
    "set_series": "Sun & Moon"
  },
  {
    "name": "Lisia",
    "number": "137",
    "rarity": "Uncommon",
    "set_name": "Celestial Storm",
    "set_series": "Sun & Moon"
  },
  {
    "name": "Lure Ball",
    "number": "138",
    "rarity": "Uncommon",
    "set_name": "Celestial Storm",
    "set_series": "Sun & Moon"
  },
  {
    "name": "The Masked Royal",
    "number": "139",
    "rarity": "Uncommon",
    "set_name": "Celestial Storm",
    "set_series": "Sun & Moon"
  },
  {
    "name": "Pok\u00e9Nav",
    "number": "140",
    "rarity": "Uncommon",
    "set_name": "Celestial Storm",
    "set_series": "Sun & Moon"
  },
  {
    "name": "Rainbow Brush",
    "number": "141",
    "rarity": "Uncommon",
    "set_name": "Celestial Storm",
    "set_series": "Sun & Moon"
  },
  {
    "name": "Rare Candy",
    "number": "142",
    "rarity": "Uncommon",
    "set_name": "Celestial Storm",
    "set_series": "Sun & Moon"
  },
  {
    "name": "Shrine of Punishment",
    "number": "143",
    "rarity": "Uncommon",
    "set_name": "Celestial Storm",
    "set_series": "Sun & Moon"
  },
  {
    "name": "Sky Pillar",
    "number": "144",
    "rarity": "Uncommon",
    "set_name": "Celestial Storm",
    "set_series": "Sun & Moon"
  },
  {
    "name": "Steven's Resolve",
    "number": "145",
    "rarity": "Rare Holo",
    "set_name": "Celestial Storm",
    "set_series": "Sun & Moon"
  },
  {
    "name": "Super Scoop Up",
    "number": "146",
    "rarity": "Uncommon",
    "set_name": "Celestial Storm",
    "set_series": "Sun & Moon"
  },
  {
    "name": "Switch",
    "number": "147",
    "rarity": "Uncommon",
    "set_name": "Celestial Storm",
    "set_series": "Sun & Moon"
  },
  {
    "name": "Tate & Liza",
    "number": "148",
    "rarity": "Uncommon",
    "set_name": "Celestial Storm",
    "set_series": "Sun & Moon"
  },
  {
    "name": "Tate & Liza",
    "number": "148a",
    "rarity": "Uncommon",
    "set_name": "Celestial Storm",
    "set_series": "Sun & Moon"
  },
  {
    "name": "TV Reporter",
    "number": "149",
    "rarity": "Uncommon",
    "set_name": "Celestial Storm",
    "set_series": "Sun & Moon"
  },
  {
    "name": "Underground Expedition",
    "number": "150",
    "rarity": "Uncommon",
    "set_name": "Celestial Storm",
    "set_series": "Sun & Moon"
  },
  {
    "name": "Rainbow Energy",
    "number": "151",
    "rarity": "Uncommon",
    "set_name": "Celestial Storm",
    "set_series": "Sun & Moon"
  },
  {
    "name": "Shiftry-GX",
    "number": "152",
    "rarity": "Rare Ultra",
    "set_name": "Celestial Storm",
    "set_series": "Sun & Moon"
  },
  {
    "name": "Blaziken-GX",
    "number": "153",
    "rarity": "Rare Ultra",
    "set_name": "Celestial Storm",
    "set_series": "Sun & Moon"
  },
  {
    "name": "Articuno-GX",
    "number": "154",
    "rarity": "Rare Ultra",
    "set_name": "Celestial Storm",
    "set_series": "Sun & Moon"
  },
  {
    "name": "Electrode-GX",
    "number": "155",
    "rarity": "Rare Ultra",
    "set_name": "Celestial Storm",
    "set_series": "Sun & Moon"
  },
  {
    "name": "Mr. Mime-GX",
    "number": "156",
    "rarity": "Rare Ultra",
    "set_name": "Celestial Storm",
    "set_series": "Sun & Moon"
  },
  {
    "name": "Banette-GX",
    "number": "157",
    "rarity": "Rare Ultra",
    "set_name": "Celestial Storm",
    "set_series": "Sun & Moon"
  },
  {
    "name": "Scizor-GX",
    "number": "158",
    "rarity": "Rare Ultra",
    "set_name": "Celestial Storm",
    "set_series": "Sun & Moon"
  },
  {
    "name": "Stakataka-GX",
    "number": "159",
    "rarity": "Rare Ultra",
    "set_name": "Celestial Storm",
    "set_series": "Sun & Moon"
  },
  {
    "name": "Rayquaza-GX",
    "number": "160",
    "rarity": "Rare Ultra",
    "set_name": "Celestial Storm",
    "set_series": "Sun & Moon"
  },
  {
    "name": "Apricorn Maker",
    "number": "161",
    "rarity": "Rare Ultra",
    "set_name": "Celestial Storm",
    "set_series": "Sun & Moon"
  },
  {
    "name": "Bill's Maintenance",
    "number": "162",
    "rarity": "Rare Ultra",
    "set_name": "Celestial Storm",
    "set_series": "Sun & Moon"
  },
  {
    "name": "Copycat",
    "number": "163",
    "rarity": "Rare Ultra",
    "set_name": "Celestial Storm",
    "set_series": "Sun & Moon"
  },
  {
    "name": "Lisia",
    "number": "164",
    "rarity": "Rare Ultra",
    "set_name": "Celestial Storm",
    "set_series": "Sun & Moon"
  },
  {
    "name": "Steven's Resolve",
    "number": "165",
    "rarity": "Rare Ultra",
    "set_name": "Celestial Storm",
    "set_series": "Sun & Moon"
  },
  {
    "name": "Tate & Liza",
    "number": "166",
    "rarity": "Rare Ultra",
    "set_name": "Celestial Storm",
    "set_series": "Sun & Moon"
  },
  {
    "name": "TV Reporter",
    "number": "167",
    "rarity": "Rare Ultra",
    "set_name": "Celestial Storm",
    "set_series": "Sun & Moon"
  },
  {
    "name": "Underground Expedition",
    "number": "168",
    "rarity": "Rare Ultra",
    "set_name": "Celestial Storm",
    "set_series": "Sun & Moon"
  },
  {
    "name": "Shiftry-GX",
    "number": "169",
    "rarity": "Rare Rainbow",
    "set_name": "Celestial Storm",
    "set_series": "Sun & Moon"
  },
  {
    "name": "Blaziken-GX",
    "number": "170",
    "rarity": "Rare Rainbow",
    "set_name": "Celestial Storm",
    "set_series": "Sun & Moon"
  },
  {
    "name": "Articuno-GX",
    "number": "171",
    "rarity": "Rare Rainbow",
    "set_name": "Celestial Storm",
    "set_series": "Sun & Moon"
  },
  {
    "name": "Electrode-GX",
    "number": "172",
    "rarity": "Rare Rainbow",
    "set_name": "Celestial Storm",
    "set_series": "Sun & Moon"
  },
  {
    "name": "Mr. Mime-GX",
    "number": "173",
    "rarity": "Rare Rainbow",
    "set_name": "Celestial Storm",
    "set_series": "Sun & Moon"
  },
  {
    "name": "Banette-GX",
    "number": "174",
    "rarity": "Rare Rainbow",
    "set_name": "Celestial Storm",
    "set_series": "Sun & Moon"
  },
  {
    "name": "Scizor-GX",
    "number": "175",
    "rarity": "Rare Rainbow",
    "set_name": "Celestial Storm",
    "set_series": "Sun & Moon"
  },
  {
    "name": "Stakataka-GX",
    "number": "176",
    "rarity": "Rare Rainbow",
    "set_name": "Celestial Storm",
    "set_series": "Sun & Moon"
  },
  {
    "name": "Rayquaza-GX",
    "number": "177",
    "rarity": "Rare Rainbow",
    "set_name": "Celestial Storm",
    "set_series": "Sun & Moon"
  },
  {
    "name": "Rayquaza-GX",
    "number": "177a",
    "rarity": "Rare Ultra",
    "set_name": "Celestial Storm",
    "set_series": "Sun & Moon"
  },
  {
    "name": "Acro Bike",
    "number": "178",
    "rarity": "Rare Secret",
    "set_name": "Celestial Storm",
    "set_series": "Sun & Moon"
  },
  {
    "name": "Hustle Belt",
    "number": "179",
    "rarity": "Rare Secret",
    "set_name": "Celestial Storm",
    "set_series": "Sun & Moon"
  },
  {
    "name": "Life Herb",
    "number": "180",
    "rarity": "Rare Secret",
    "set_name": "Celestial Storm",
    "set_series": "Sun & Moon"
  },
  {
    "name": "Pok\u00e9Nav",
    "number": "181",
    "rarity": "Rare Secret",
    "set_name": "Celestial Storm",
    "set_series": "Sun & Moon"
  },
  {
    "name": "Rainbow Brush",
    "number": "182",
    "rarity": "Rare Secret",
    "set_name": "Celestial Storm",
    "set_series": "Sun & Moon"
  },
  {
    "name": "Rainbow Energy",
    "number": "183",
    "rarity": "Rare Secret",
    "set_name": "Celestial Storm",
    "set_series": "Sun & Moon"
  }
]